<annotation>
	<folder>train</folder>
	<filename>19.jpg</filename>
	<path>C:\Users\apolonia\ComputerVision\0_Practice\object_detecteion_medicine_v4\data\images\train\19.jpg</path>
	<source>
		<database>Unknown</database>
	</source>
	<size>
		<width>800</width>
		<height>600</height>
		<depth>3</depth>
	</size>
	<segmented>0</segmented>
	<object>
		<name>pill_tylenol</name>
		<pose>Unspecified</pose>
		<truncated>0</truncated>
		<difficult>0</difficult>
		<bndbox>
			<xmin>255</xmin>
			<ymin>140</ymin>
			<xmax>395</xmax>
			<ymax>226</ymax>
		</bndbox>
	</object>
	<object>
		<name>pill_ezn</name>
		<pose>Unspecified</pose>
		<truncated>0</truncated>
		<difficult>0</difficult>
		<bndbox>
			<xmin>457</xmin>
			<ymin>147</ymin>
			<xmax>579</xmax>
			<ymax>240</ymax>
		</bndbox>
	</object>
	<object>
		<name>fucidin</name>
		<pose>Unspecified</pose>
		<truncated>0</truncated>
		<difficult>0</difficult>
		<bndbox>
			<xmin>204</xmin>
			<ymin>398</ymin>
			<xmax>639</xmax>
			<ymax>521</ymax>
		</bndbox>
	</object>
</annotation>
